django_dreiattest-1.2.5.dist-info/licenses/LICENSE
dreiattest/__init__.py
dreiattest/__version__.py
dreiattest/apps.py
dreiattest/decorators.py
dreiattest/device_session.py
dreiattest/exceptions.py
dreiattest/generate_config.py
dreiattest/helpers.py
dreiattest/key.py
dreiattest/middlewares.py
dreiattest/models.py
dreiattest/nonce.py
dreiattest/plugins.py
dreiattest/settings.py
dreiattest/urls.py
dreiattest/views.py
dreiattest/migrations/0001_initial.py
dreiattest/migrations/0002_auto_20210225_0949.py
dreiattest/migrations/0003_auto_20210225_1008.py
dreiattest/migrations/0004_auto_20210225_1246.py
dreiattest/migrations/0005_key_driver.py
dreiattest/migrations/0006_rename_devicesession_user_id_session_id_dreiattest__user_id_0e3f7c_idx.py
dreiattest/migrations/__init__.py
django_dreiattest-1.2.5.dist-info/METADATA
django_dreiattest-1.2.5.dist-info/WHEEL
django_dreiattest-1.2.5.dist-info/top_level.txt
django_dreiattest-1.2.5.dist-info/RECORD
